<?xml version='1.0' encoding='utf-8'?>
<TextureAtlas imagePath="mcbf.png">
<SubTexture name="mcbf idle0000" x="0" y="0" width="187" height="202" frameX="-758" frameY="-362" frameWidth="1280" frameHeight="720" />
<SubTexture name="mcbf idle0001" x="187" y="0" width="189" height="203" frameX="-757" frameY="-361" frameWidth="1280" frameHeight="720" />
<SubTexture name="mcbf idle0002" x="376" y="0" width="190" height="204" frameX="-757" frameY="-360" frameWidth="1280" frameHeight="720" />
<SubTexture name="mcbf idle0003" x="566" y="0" width="190" height="204" frameX="-757" frameY="-360" frameWidth="1280" frameHeight="720" />
<SubTexture name="mcbf idle0004" x="756" y="0" width="190" height="204" frameX="-757" frameY="-360" frameWidth="1280" frameHeight="720" />
<SubTexture name="mcbf idle0005" x="946" y="0" width="191" height="205" frameX="-757" frameY="-359" frameWidth="1280" frameHeight="720" />
<SubTexture name="mcbf idle0006" x="1137" y="0" width="190" height="205" frameX="-757" frameY="-359" frameWidth="1280" frameHeight="720" />
<SubTexture name="mcbf idle0007" x="1327" y="0" width="188" height="206" frameX="-758" frameY="-358" frameWidth="1280" frameHeight="720" />
<SubTexture name="mcbf idle0008" x="0" y="206" width="187" height="205" frameX="-758" frameY="-359" frameWidth="1280" frameHeight="720" />
<SubTexture name="mcbf idle0009" x="187" y="206" width="187" height="205" frameX="-758" frameY="-359" frameWidth="1280" frameHeight="720" />
<SubTexture name="mcbf idle0010" x="374" y="206" width="187" height="205" frameX="-758" frameY="-359" frameWidth="1280" frameHeight="720" />
<SubTexture name="mcbf up0000" x="561" y="206" width="171" height="210" frameX="-776" frameY="-354" frameWidth="1280" frameHeight="720" />
<SubTexture name="mcbf up0001" x="732" y="206" width="172" height="213" frameX="-777" frameY="-351" frameWidth="1280" frameHeight="720" />
<SubTexture name="mcbf up0002" x="904" y="206" width="172" height="213" frameX="-777" frameY="-351" frameWidth="1280" frameHeight="720" />
<SubTexture name="mcbf up0003" x="1076" y="206" width="172" height="212" frameX="-777" frameY="-352" frameWidth="1280" frameHeight="720" />
<SubTexture name="mcbf up0004" x="1248" y="206" width="172" height="211" frameX="-777" frameY="-353" frameWidth="1280" frameHeight="720" />
<SubTexture name="mcbf up0005" x="0" y="419" width="173" height="211" frameX="-776" frameY="-353" frameWidth="1280" frameHeight="720" />
<SubTexture name="mcbf up0006" x="173" y="419" width="172" height="210" frameX="-776" frameY="-354" frameWidth="1280" frameHeight="720" />
<SubTexture name="mcbf up0007" x="345" y="419" width="172" height="210" frameX="-776" frameY="-354" frameWidth="1280" frameHeight="720" />
<SubTexture name="mcbf up0008" x="517" y="419" width="171" height="210" frameX="-776" frameY="-354" frameWidth="1280" frameHeight="720" />
<SubTexture name="mcbf up0009" x="688" y="419" width="171" height="210" frameX="-776" frameY="-354" frameWidth="1280" frameHeight="720" />
<SubTexture name="mcbf up0010" x="561" y="206" width="171" height="210" frameX="-776" frameY="-354" frameWidth="1280" frameHeight="720" />
<SubTexture name="mcbf down0000" x="859" y="419" width="168" height="205" frameX="-775" frameY="-359" frameWidth="1280" frameHeight="720" />
<SubTexture name="mcbf down0001" x="1027" y="419" width="168" height="205" frameX="-775" frameY="-359" frameWidth="1280" frameHeight="720" />
<SubTexture name="mcbf down0002" x="1195" y="419" width="169" height="205" frameX="-775" frameY="-359" frameWidth="1280" frameHeight="720" />
<SubTexture name="mcbf down0003" x="0" y="630" width="169" height="205" frameX="-775" frameY="-359" frameWidth="1280" frameHeight="720" />
<SubTexture name="mcbf down0004" x="169" y="630" width="168" height="205" frameX="-776" frameY="-359" frameWidth="1280" frameHeight="720" />
<SubTexture name="mcbf down0005" x="337" y="630" width="168" height="205" frameX="-776" frameY="-359" frameWidth="1280" frameHeight="720" />
<SubTexture name="mcbf down0006" x="505" y="630" width="168" height="205" frameX="-776" frameY="-359" frameWidth="1280" frameHeight="720" />
<SubTexture name="mcbf down0007" x="673" y="630" width="168" height="205" frameX="-775" frameY="-359" frameWidth="1280" frameHeight="720" />
<SubTexture name="mcbf down0008" x="841" y="630" width="168" height="205" frameX="-775" frameY="-359" frameWidth="1280" frameHeight="720" />
<SubTexture name="mcbf down0009" x="1009" y="630" width="168" height="205" frameX="-775" frameY="-359" frameWidth="1280" frameHeight="720" />
<SubTexture name="mcbf down0010" x="859" y="419" width="168" height="205" frameX="-775" frameY="-359" frameWidth="1280" frameHeight="720" />
<SubTexture name="mcbf left0000" x="1177" y="630" width="167" height="204" frameX="-766" frameY="-360" frameWidth="1280" frameHeight="720" />
<SubTexture name="mcbf left0001" x="0" y="835" width="167" height="204" frameX="-766" frameY="-360" frameWidth="1280" frameHeight="720" />
<SubTexture name="mcbf left0002" x="167" y="835" width="166" height="204" frameX="-767" frameY="-360" frameWidth="1280" frameHeight="720" />
<SubTexture name="mcbf left0003" x="333" y="835" width="167" height="204" frameX="-767" frameY="-360" frameWidth="1280" frameHeight="720" />
<SubTexture name="mcbf left0004" x="500" y="835" width="167" height="204" frameX="-767" frameY="-360" frameWidth="1280" frameHeight="720" />
<SubTexture name="mcbf left0005" x="667" y="835" width="167" height="204" frameX="-767" frameY="-360" frameWidth="1280" frameHeight="720" />
<SubTexture name="mcbf left0006" x="834" y="835" width="167" height="204" frameX="-767" frameY="-360" frameWidth="1280" frameHeight="720" />
<SubTexture name="mcbf left0007" x="1001" y="835" width="167" height="203" frameX="-766" frameY="-361" frameWidth="1280" frameHeight="720" />
<SubTexture name="mcbf left0008" x="1168" y="835" width="167" height="204" frameX="-766" frameY="-360" frameWidth="1280" frameHeight="720" />
<SubTexture name="mcbf left0009" x="0" y="1039" width="167" height="204" frameX="-766" frameY="-360" frameWidth="1280" frameHeight="720" />
<SubTexture name="mcbf left0010" x="1177" y="630" width="167" height="204" frameX="-766" frameY="-360" frameWidth="1280" frameHeight="720" />
<SubTexture name="mcbf right0000" x="167" y="1039" width="173" height="205" frameX="-786" frameY="-359" frameWidth="1280" frameHeight="720" />
<SubTexture name="mcbf right0001" x="340" y="1039" width="172" height="206" frameX="-787" frameY="-358" frameWidth="1280" frameHeight="720" />
<SubTexture name="mcbf right0002" x="512" y="1039" width="173" height="206" frameX="-787" frameY="-358" frameWidth="1280" frameHeight="720" />
<SubTexture name="mcbf right0003" x="685" y="1039" width="173" height="206" frameX="-787" frameY="-358" frameWidth="1280" frameHeight="720" />
<SubTexture name="mcbf right0004" x="858" y="1039" width="173" height="205" frameX="-786" frameY="-359" frameWidth="1280" frameHeight="720" />
<SubTexture name="mcbf right0005" x="1031" y="1039" width="173" height="205" frameX="-786" frameY="-359" frameWidth="1280" frameHeight="720" />
<SubTexture name="mcbf right0006" x="1204" y="1039" width="173" height="205" frameX="-786" frameY="-359" frameWidth="1280" frameHeight="720" />
<SubTexture name="mcbf right0007" x="0" y="1245" width="173" height="205" frameX="-786" frameY="-359" frameWidth="1280" frameHeight="720" />
<SubTexture name="mcbf right0008" x="173" y="1245" width="172" height="205" frameX="-786" frameY="-359" frameWidth="1280" frameHeight="720" />
<SubTexture name="mcbf right0009" x="345" y="1245" width="173" height="205" frameX="-786" frameY="-359" frameWidth="1280" frameHeight="720" />
<SubTexture name="mcbf right0010" x="167" y="1039" width="173" height="205" frameX="-786" frameY="-359" frameWidth="1280" frameHeight="720" />
<SubTexture name="mcbf miss0000" x="518" y="1245" width="178" height="203" frameX="-767" frameY="-361" frameWidth="1280" frameHeight="720" />
<SubTexture name="mcbf miss0001" x="696" y="1245" width="179" height="203" frameX="-767" frameY="-361" frameWidth="1280" frameHeight="720" />
<SubTexture name="mcbf miss0002" x="875" y="1245" width="180" height="204" frameX="-766" frameY="-360" frameWidth="1280" frameHeight="720" />
<SubTexture name="mcbf miss0003" x="1055" y="1245" width="180" height="204" frameX="-766" frameY="-360" frameWidth="1280" frameHeight="720" />
<SubTexture name="mcbf miss0004" x="1235" y="1245" width="180" height="204" frameX="-766" frameY="-360" frameWidth="1280" frameHeight="720" />
<SubTexture name="mcbf miss0005" x="0" y="1450" width="180" height="205" frameX="-766" frameY="-359" frameWidth="1280" frameHeight="720" />
<SubTexture name="mcbf miss0006" x="180" y="1450" width="180" height="205" frameX="-766" frameY="-359" frameWidth="1280" frameHeight="720" />
<SubTexture name="mcbf miss0007" x="360" y="1450" width="179" height="205" frameX="-767" frameY="-359" frameWidth="1280" frameHeight="720" />
<SubTexture name="mcbf miss0008" x="539" y="1450" width="178" height="205" frameX="-767" frameY="-359" frameWidth="1280" frameHeight="720" />
<SubTexture name="mcbf miss0009" x="717" y="1450" width="178" height="205" frameX="-767" frameY="-359" frameWidth="1280" frameHeight="720" />
<SubTexture name="mcbf miss0010" x="895" y="1450" width="178" height="205" frameX="-767" frameY="-359" frameWidth="1280" frameHeight="720" />
</TextureAtlas>
