{
	"animations": [
		{
			"offsets": [0, 0],
			"loop": false,
			"fps": 24,
			"anim": "idle",
			"indices": [],
			"name": "idle"
		},
		{
			"offsets": [32, 14],
			"loop": false,
			"fps": 24,
			"anim": "singLEFT",
			"indices": [],
			"name": "left"
		},
		{
			"offsets": [-48, -45],
			"loop": false,
			"fps": 24,
			"anim": "singDOWN",
			"indices": [],
			"name": "down"
		},
		{
			"offsets": [-96, -36],
			"loop": false,
			"fps": 24,
			"anim": "singRIGHT",
			"indices": [],
			"name": "right"
		},
		{
			"offsets": [-94, 31],
			"loop": false,
			"fps": 24,
			"anim": "singUP",
			"indices": [],
			"name": "up"
		}
	],
	"vocals_file": "",
	"no_antialiasing": false,
	"image": "characters/alex",
	"position": [-50, 170],
	"healthicon": "alex",
	"flip_x": false,
	"healthbar_colors": [255, 193, 77],
	"camera_position": [10, 60],
	"sing_duration": 4,
	"scale": 1,
	"_editor_isPlayer": false
}